server.py
simple_levi-0.2.0.dist-info/METADATA
simple_levi-0.2.0.dist-info/WHEEL
simple_levi-0.2.0.dist-info/top_level.txt
simple_levi-0.2.0.dist-info/RECORD
